netom/.github/workflows/tests.yml
netom/__init__.py
netom/__main__.py
netom/cli.py
netom/exception.py
netom/models.py
netom/templates/netom0/Pipfile
netom/templates/netom0/bird1-0/bgp/neighbors.j2
netom/templates/netom0/junos-0/bgp/neighbors.j2
netom/templates/netom0/junos-set-0/bgp/neighbors.j2
netom/templates/netom0/sros-classic-0/bgp/neighbors.j2
netom/templates/netom0/sros-md-0/bgp/neighbors.j2
netom/templates/netom0/sros-md-fc-0/bgp/neighbors.j2
netom-0.2.0.dist-info/entry_points.txt
netom-0.2.0.dist-info/LICENSE
netom-0.2.0.dist-info/WHEEL
netom-0.2.0.dist-info/METADATA
netom-0.2.0.dist-info/RECORD
