Metadata-Version: 2.1
Name: netom
Version: 0.2.0
Summary: network object models
License: Apache-2.0
Author: 20C
Author-email: code@20c.com
Requires-Python: >=3.6,<4.0
Classifier: Development Status :: 4 - Beta
Classifier: Intended Audience :: Developers
Classifier: Intended Audience :: System Administrators
Classifier: Intended Audience :: Telecommunications Industry
Classifier: License :: OSI Approved :: Apache Software License
Classifier: Programming Language :: Python :: 3
Classifier: Programming Language :: Python :: 3.6
Classifier: Programming Language :: Python :: 3.7
Classifier: Programming Language :: Python :: 3.8
Classifier: Programming Language :: Python :: 3.9
Classifier: Topic :: Internet
Classifier: Topic :: Software Development :: Libraries :: Python Modules
Requires-Dist: Jinja2 (>=2.10.1,<3.0.0)
Requires-Dist: confu (>=1.7.1,<2.0.0)
Requires-Dist: munge (>=1.1.0,<2.0.0)
Requires-Dist: tmpl (>=0.3.0,<0.4.0)
